aws_organizations/__init__.py
aws_organizations/_version.py
aws_organizations/api.py
aws_organizations/org_struct.py
aws_organizations/paths.py
aws_organizations/better_boto/__init__.py
aws_organizations/better_boto/api.py
aws_organizations/better_boto/model.py
aws_organizations/better_boto/org.py
aws_organizations/better_boto/org_unit.py
aws_organizations/docs/__init__.py
aws_organizations/tests/__init__.py
aws_organizations/tests/helper.py
aws_organizations/vendor/__init__.py
aws_organizations/vendor/pytest_cov_helper.py
aws_organizations-0.4.2.dist-info/licenses/AUTHORS.rst
aws_organizations-0.4.2.dist-info/licenses/LICENSE.txt
aws_organizations-0.4.2.dist-info/METADATA
aws_organizations-0.4.2.dist-info/WHEEL
aws_organizations-0.4.2.dist-info/top_level.txt
aws_organizations-0.4.2.dist-info/RECORD
